<annotation>
    <folder>mages</folder>
    <filename>1570439003942.png</filename>
    <path>/client/exampleRobot/images/1570439003942.png</path>
    <source>
        <database>Unknown</database>
    </source>
    <size>
        <width>500</width>
        <height>300</height>
        <depth>3</depth>
    </size>
    <segmented>0</segmented>
    <object>
        <name>tommad</name>
        <pose>Unspecified</pose>
        <truncated>0</truncated>
        <difficult>0</difficult>
        <bndbox>
            <xmin>349</xmin>
            <ymin>173</ymin>
            <xmax>590</xmax>
            <ymax>480</ymax>
        </bndbox>
    </object>
</annotation>